{
  "city_id": "johannesburg",
  "city_name": "Johannesburg",
  "tier": "medium",
  "problem_clusters": [
    "power_cuts",
    "inequality",
    "crime"
  ],
  "city_personality": {
    "voice": "cynical-hustler",
    "humor_style": "loud_populist",
    "media_outlet": "The Star",
    "government_body": "City of Johannesburg Metropolitan Municipality",
    "landmark": "Hillbrow Tower",
    "primary_industry_workers": "minibus taxi drivers and informal traders",
    "slang_reaction": "Eish, this government is a joke, chommie."
  },
  "opening_sequence": {
    "title": "Welcome to Egoli, Mayor",
    "intro": "The City of Gold is rusting. Load shedding plunges the streets into darkness, the infrastructure is collapsing, and the gap between Sandton and Soweto has never been wider.",
    "starting_stats": {
      "approval_rating": 45,
      "budget": 500,
      "advisor_trust_levels": {
        "finance": 55,
        "military_liaison": 50,
        "urban_planning": 45,
        "transport": 60,
        "religious_affairs": 40
      }
    }
  },
  "advisors": [
    {
      "id": "finance",
      "name": "Thabo Mofokeng",
      "domain": "Finance & Tenders",
      "archetype": "Schemer",
      "hidden_agenda": "Awarding lucrative municipal contracts to his cousin's shell companies.",
      "betrayal_trigger": "Implementing a strict, open-source tender review process.",
      "competence_rating": 7,
      "relationship_meter": 50,
      "dialogue": {
        "briefing": [
          "Revenue collection in the townships is practically zero.",
          "We have a massive shortfall this quarter.",
          "The tender for the new billing system is ready for your signature."
        ],
        "agreement": [
          "Good business sense.",
          "The market will respond well."
        ],
        "disagreement": [
          "You are leaving money on the table.",
          "This will upset very important people."
        ],
        "betrayal": "You closed the tap. I'm joining the opposition and taking my donors with me.",
        "roast": [
          "You run this city like a spaza shop.",
          "Even the pigeons manage their crumbs better than you."
        ],
        "scandal_reaction": [
          "Deny, deflect, delay.",
          "Let's blame the previous administration."
        ]
      }
    },
    {
      "id": "military_liaison",
      "name": "Captain Hendrik Van Der Merwe",
      "domain": "Metro Police (JMPD)",
      "archetype": "Hardliner",
      "hidden_agenda": "Privatizing security in affluent suburbs to benefit his former colleagues.",
      "betrayal_trigger": "Banning private security companies from operating on public roads.",
      "competence_rating": 8,
      "relationship_meter": 45,
      "dialogue": {
        "briefing": [
          "Cable theft has left the inner city dark again.",
          "Illegal mining operations are destabilizing the roads.",
          "Crime stats in the CBD are through the roof."
        ],
        "agreement": [
          "Law and order, Mayor.",
          "We will deploy immediately."
        ],
        "disagreement": [
          "You are tying our hands.",
          "The criminals are laughing at us."
        ],
        "betrayal": "You prefer chaos to order. I'm resigning to run a private firm that actually works.",
        "roast": [
          "You are softer than a marshamallow.",
          "This city is a crime scene and you are the suspect."
        ],
        "scandal_reaction": [
          "No comment to the press.",
          "Keep the sirens loud to distract them."
        ]
      }
    },
    {
      "id": "urban_planning",
      "name": "Lerato Ndlovu",
      "domain": "Housing & Services",
      "archetype": "Idealist",
      "hidden_agenda": "Expropriating abandoned inner-city buildings for social housing.",
      "betrayal_trigger": "Selling off inner-city hijacked buildings to private developers instead of converting them.",
      "competence_rating": 7,
      "relationship_meter": 55,
      "dialogue": {
        "briefing": [
          "The housing backlog is over 300,000 units.",
          "Informal settlements are expanding along the highways.",
          "We need to reclaim the hijacked buildings in Hillbrow."
        ],
        "agreement": [
          "A victory for the people.",
          "Dignity restored."
        ],
        "disagreement": [
          "You are forgetting the poor.",
          "This is just apartheid spatial planning with a new coat of paint."
        ],
        "betrayal": "You sold out the working class to the developers. I'll see you in the streets.",
        "roast": [
          "You build mansions while the people live in shacks.",
          "Your vision for the city is completely blind."
        ],
        "scandal_reaction": [
          "This administration is morally bankrupt.",
          "I need to distance myself from this."
        ]
      }
    },
    {
      "id": "transport",
      "name": "Sipho 'Vusi' Zungu",
      "domain": "Transit & Taxi Associations",
      "archetype": "Fixer",
      "hidden_agenda": "Ensuring the municipal bus service (Rea Vaya) never outcompetes the minibus taxis.",
      "betrayal_trigger": "Massively expanding the Rea Vaya routes into heavily controlled taxi territory.",
      "competence_rating": 6,
      "relationship_meter": 60,
      "dialogue": {
        "briefing": [
          "The taxi bosses are threatening a strike over petrol prices.",
          "Potholes on the M1 are destroying suspensions.",
          "Traffic lights are out across Sandton due to load shedding."
        ],
        "agreement": [
          "Sharp, sharp.",
          "The associations will be pleased."
        ],
        "disagreement": [
          "You are poking the bear, Mayor.",
          "Expect burning tires tomorrow."
        ],
        "betrayal": "You crossed the taxi bosses. Good luck governing a city that can't move.",
        "roast": [
          "You are driving this city into a ditch.",
          "Your policies have more potholes than our roads."
        ],
        "scandal_reaction": [
          "Eish, this is bad.",
          "I'll arrange a safe house."
        ]
      }
    },
    {
      "id": "religious_affairs",
      "name": "Bishop Desmond Khumalo",
      "domain": "Community Liaison",
      "archetype": "Moralist",
      "hidden_agenda": "Securing a massive municipal grant for his mega-church's 'community outreach' program.",
      "betrayal_trigger": "Cutting all funding to faith-based organizations to balance the budget.",
      "competence_rating": 5,
      "relationship_meter": 40,
      "dialogue": {
        "briefing": [
          "The community is losing hope, Mayor.",
          "Poverty is driving our youth to nyaope (drugs).",
          "We must lead with compassion."
        ],
        "agreement": [
          "Amen. A blessed choice.",
          "The congregation will pray for you."
        ],
        "disagreement": [
          "You lack spiritual guidance.",
          "The people will suffer for this."
        ],
        "betrayal": "You have turned your back on the faithful. My sermons will reflect this.",
        "roast": [
          "Even prayer cannot save your approval ratings.",
          "You are morally bankrupt."
        ],
        "scandal_reaction": [
          "God sees all.",
          "Repentance is necessary."
        ]
      }
    }
  ],
  "decisions": [
    {
      "id": "load_shedding_mitigation",
      "title": "The Power Crisis",
      "body": "The national grid is failing, causing daily blackouts (load shedding). The city must find a way to keep the lights on.",
      "turn_available": 2,
      "unlock_flag": null,
      "options": [
        {
          "label": "Purchase expensive diesel to run emergency generators for critical infrastructure.",
          "tag": "SAFE",
          "consequences": {
            "approval_delta": 10,
            "budget_delta": -80,
            "advisor_effects": [
              {
                "advisor_id": "finance",
                "trust_delta": -10,
                "betrayal_risk_delta": 5
              }
            ],
            "scandal_risk": 15,
            "public_reaction": "At least the traffic lights are working."
          }
        },
        {
          "label": "Sign a massive contract with independent power producers (IPPs).",
          "tag": "BOLD",
          "consequences": {
            "approval_delta": 15,
            "budget_delta": -150,
            "advisor_effects": [
              {
                "advisor_id": "urban_planning",
                "trust_delta": 15,
                "betrayal_risk_delta": -5
              }
            ],
            "scandal_risk": 30,
            "public_reaction": "Finally, we are ditching the national utility."
          }
        },
        {
          "label": "Cut off power entirely to non-paying townships to stabilize the grid.",
          "tag": "CHAOS",
          "consequences": {
            "approval_delta": -25,
            "budget_delta": 50,
            "advisor_effects": [
              {
                "advisor_id": "urban_planning",
                "trust_delta": -25,
                "betrayal_risk_delta": 20
              }
            ],
            "scandal_risk": 60,
            "public_reaction": "This means war! We will burn the substations!"
          }
        }
      ]
    },
    {
      "id": "hijacked_buildings",
      "title": "The Hillbrow Hijackings",
      "body": "Criminal syndicates have taken over dozens of inner-city apartment buildings, collecting rent illegally while the buildings decay into slums.",
      "turn_available": 3,
      "unlock_flag": null,
      "options": [
        {
          "label": "Cut off water and electricity to force them out.",
          "tag": "SAFE",
          "consequences": {
            "approval_delta": -5,
            "budget_delta": 10,
            "advisor_effects": [
              {
                "advisor_id": "urban_planning",
                "trust_delta": -15,
                "betrayal_risk_delta": 10
              }
            ],
            "scandal_risk": 20,
            "public_reaction": "Cruel. Innocent people are suffering in there too."
          }
        },
        {
          "label": "Launch massive JMPD raids to physically evict the syndicates.",
          "tag": "BOLD",
          "consequences": {
            "approval_delta": 15,
            "budget_delta": -60,
            "advisor_effects": [
              {
                "advisor_id": "military_liaison",
                "trust_delta": 20,
                "betrayal_risk_delta": -10
              }
            ],
            "scandal_risk": 40,
            "public_reaction": "Clean up the streets! Finally!"
          }
        },
        {
          "label": "Offer amnesty and hand the title deeds over to the syndicates to 'formalize' them.",
          "tag": "CHAOS",
          "consequences": {
            "approval_delta": -30,
            "budget_delta": 40,
            "advisor_effects": [
              {
                "advisor_id": "military_liaison",
                "trust_delta": -25,
                "betrayal_risk_delta": 20
              }
            ],
            "scandal_risk": 80,
            "public_reaction": "We just rewarded criminals with property!"
          }
        }
      ]
    },
    {
      "id": "cable_theft",
      "title": "The Copper Syndicate",
      "body": "Heavily armed syndicates are stealing kilometers of copper cable, leaving entire suburbs without power or internet.",
      "turn_available": 5,
      "unlock_flag": null,
      "options": [
        {
          "label": "Hire private security to guard major substations.",
          "tag": "SAFE",
          "consequences": {
            "approval_delta": 10,
            "budget_delta": -50,
            "advisor_effects": [
              {
                "advisor_id": "military_liaison",
                "trust_delta": 15,
                "betrayal_risk_delta": -5
              }
            ],
            "scandal_risk": 15,
            "public_reaction": "Expensive, but we need our internet back."
          }
        },
        {
          "label": "Ban all scrap metal yards in the city to destroy the market.",
          "tag": "BOLD",
          "consequences": {
            "approval_delta": 5,
            "budget_delta": -20,
            "advisor_effects": [
              {
                "advisor_id": "finance",
                "trust_delta": -15,
                "betrayal_risk_delta": 10
              }
            ],
            "scandal_risk": 30,
            "public_reaction": "Legit businesses are paying the price."
          }
        },
        {
          "label": "Electrify the exposed cables with lethal voltage to deter thieves.",
          "tag": "CHAOS",
          "consequences": {
            "approval_delta": -15,
            "budget_delta": -10,
            "advisor_effects": [
              {
                "advisor_id": "urban_planning",
                "trust_delta": -20,
                "betrayal_risk_delta": 15
              }
            ],
            "scandal_risk": 70,
            "public_reaction": "People are dying in the streets!"
          }
        }
      ]
    },
    {
      "id": "pothole_epidemic",
      "title": "The Pothole Epidemic",
      "body": "Heavy rains and neglected maintenance have turned the roads into an obstacle course, damaging thousands of vehicles.",
      "turn_available": 6,
      "unlock_flag": null,
      "options": [
        {
          "label": "Launch a slow, internal municipal patching program.",
          "tag": "SAFE",
          "consequences": {
            "approval_delta": -5,
            "budget_delta": -30,
            "advisor_effects": [
              {
                "advisor_id": "transport",
                "trust_delta": 5,
                "betrayal_risk_delta": 0
              }
            ],
            "scandal_risk": 10,
            "public_reaction": "Too little, too late. They wash away in the next rain."
          }
        },
        {
          "label": "Privatize road maintenance to a major corporate sponsor.",
          "tag": "BOLD",
          "consequences": {
            "approval_delta": 15,
            "budget_delta": 0,
            "advisor_effects": [
              {
                "advisor_id": "finance",
                "trust_delta": 15,
                "betrayal_risk_delta": -10
              }
            ],
            "scandal_risk": 25,
            "public_reaction": "Brought to you by Discovery Health. Whatever works."
          }
        },
        {
          "label": "Tell citizens to fix the potholes themselves and deduct it from their rates.",
          "tag": "CHAOS",
          "consequences": {
            "approval_delta": -20,
            "budget_delta": 40,
            "advisor_effects": [
              {
                "advisor_id": "finance",
                "trust_delta": -10,
                "betrayal_risk_delta": 5
              }
            ],
            "scandal_risk": 50,
            "public_reaction": "What are we paying taxes for?!"
          }
        }
      ]
    },
    {
      "id": "taxi_violence",
      "title": "Taxi Route Wars",
      "body": "Rival minibus taxi associations are shooting at each other over lucrative routes, catching commuters in the crossfire.",
      "turn_available": 9,
      "unlock_flag": null,
      "options": [
        {
          "label": "Mediate a peace deal and grant both sides more routes.",
          "tag": "SAFE",
          "consequences": {
            "approval_delta": 5,
            "budget_delta": -20,
            "advisor_effects": [
              {
                "advisor_id": "transport",
                "trust_delta": 15,
                "betrayal_risk_delta": -10
              }
            ],
            "scandal_risk": 10,
            "public_reaction": "Appeasing the warlords again."
          }
        },
        {
          "label": "Deploy the military to shut down the contested taxi ranks entirely.",
          "tag": "BOLD",
          "consequences": {
            "approval_delta": -10,
            "budget_delta": -70,
            "advisor_effects": [
              {
                "advisor_id": "transport",
                "trust_delta": -25,
                "betrayal_risk_delta": 20
              }
            ],
            "scandal_risk": 40,
            "public_reaction": "How do we get to work now?!"
          }
        },
        {
          "label": "Subsidize the heavily armed private security of one side to crush the other.",
          "tag": "CHAOS",
          "consequences": {
            "approval_delta": -25,
            "budget_delta": -50,
            "advisor_effects": [
              {
                "advisor_id": "military_liaison",
                "trust_delta": -20,
                "betrayal_risk_delta": 15
              }
            ],
            "scandal_risk": 80,
            "public_reaction": "The city is officially funding gang warfare."
          }
        }
      ]
    }
  ],
  "crises": [
    {
      "id": "xenophobic_riots",
      "name": "Outbreak of Xenophobic Violence",
      "trigger": "Tensions over unemployment have boiled over into violent attacks on foreign-owned shops.",
      "description": "Mobs are looting and burning stores in the CBD and Alexandra. Foreign nationals are fleeing, and the international community is threatening sanctions. The police are vastly outnumbered.",
      "turn_min": 4,
      "turn_max": 7,
      "war_mode": false,
      "options": [
        {
          "id": "A",
          "label": "Condemn the violence and set up safe camps for the displaced.",
          "tag": "SAFE",
          "consequences": {
            "approval_delta": 5,
            "budget_delta": -80,
            "scandal_risk": 15,
            "advisor_effects": [
              {
                "advisor_id": "urban_planning",
                "trust_delta": 15,
                "betrayal_risk_delta": -10
              }
            ]
          }
        },
        {
          "id": "B",
          "label": "Order the police to use live ammunition to stop the looters.",
          "tag": "BOLD",
          "consequences": {
            "approval_delta": -15,
            "budget_delta": -40,
            "scandal_risk": 60,
            "advisor_effects": [
              {
                "advisor_id": "military_liaison",
                "trust_delta": 20,
                "betrayal_risk_delta": -15
              }
            ]
          }
        },
        {
          "id": "C",
          "label": "Pandering to the mob, promise mass deportations of undocumented immigrants.",
          "tag": "CHAOS",
          "consequences": {
            "approval_delta": 20,
            "budget_delta": 0,
            "scandal_risk": 80,
            "advisor_effects": [
              {
                "advisor_id": "urban_planning",
                "trust_delta": -30,
                "betrayal_risk_delta": 25
              }
            ]
          }
        }
      ]
    },
    {
      "id": "water_system_collapse",
      "name": "Rand Water Reservoir Collapse",
      "trigger": "Total failure of the pumping stations has left 80% of the city without running water.",
      "description": "Hospitals are cancelling surgeries. Schools are closed. Citizens are queuing for hours at erratic water tankers, and desperation is leading to clashes in the streets.",
      "turn_min": 6,
      "turn_max": 9,
      "war_mode": false,
      "options": [
        {
          "id": "A",
          "label": "Deploy hundreds of emergency water tankers at massive cost.",
          "tag": "SAFE",
          "consequences": {
            "approval_delta": 10,
            "budget_delta": -150,
            "scandal_risk": 10,
            "advisor_effects": [
              {
                "advisor_id": "finance",
                "trust_delta": -20,
                "betrayal_risk_delta": 15
              }
            ]
          }
        },
        {
          "id": "B",
          "label": "Implement strict water rationing: affluent areas cut to supply the hospitals.",
          "tag": "BOLD",
          "consequences": {
            "approval_delta": -10,
            "budget_delta": -30,
            "scandal_risk": 30,
            "advisor_effects": [
              {
                "advisor_id": "finance",
                "trust_delta": -15,
                "betrayal_risk_delta": 10
              }
            ]
          }
        },
        {
          "id": "C",
          "label": "Blame the national utility and urge citizens to collect rainwater.",
          "tag": "CHAOS",
          "consequences": {
            "approval_delta": -35,
            "budget_delta": 0,
            "scandal_risk": 70,
            "advisor_effects": [
              {
                "advisor_id": "urban_planning",
                "trust_delta": -25,
                "betrayal_risk_delta": 20
              }
            ]
          }
        }
      ]
    },
    {
      "id": "municipal_strike",
      "name": "Massive Municipal Strike",
      "trigger": "SAMWU (the municipal workers union) has gone on strike, bringing the city to a halt.",
      "description": "Trash is piling up in the streets, buses aren't running, and licensing departments are closed. The union demands a 15% wage increase that will bankrupt the city.",
      "turn_min": 8,
      "turn_max": 11,
      "war_mode": false,
      "options": [
        {
          "id": "A",
          "label": "Cave to the demands and take on massive debt to pay them.",
          "tag": "SAFE",
          "consequences": {
            "approval_delta": 15,
            "budget_delta": -250,
            "scandal_risk": 15,
            "advisor_effects": [
              {
                "advisor_id": "finance",
                "trust_delta": -30,
                "betrayal_risk_delta": 25
              }
            ]
          }
        },
        {
          "id": "B",
          "label": "Refuse the demands and fire striking workers, hiring private contractors.",
          "tag": "BOLD",
          "consequences": {
            "approval_delta": -20,
            "budget_delta": 50,
            "scandal_risk": 40,
            "advisor_effects": [
              {
                "advisor_id": "urban_planning",
                "trust_delta": -20,
                "betrayal_risk_delta": 15
              }
            ]
          }
        },
        {
          "id": "C",
          "label": "Deploy the police to violently break up the union blockades.",
          "tag": "CHAOS",
          "consequences": {
            "approval_delta": -30,
            "budget_delta": -20,
            "scandal_risk": 80,
            "advisor_effects": [
              {
                "advisor_id": "military_liaison",
                "trust_delta": 15,
                "betrayal_risk_delta": -5
              }
            ]
          }
        }
      ]
    },
    {
      "id": "coalition_collapse",
      "name": "Coalition Government Collapse",
      "trigger": "Your fragile political coalition has shattered, and a motion of no confidence is looming.",
      "description": "Small kingmaker parties are demanding impossible concessions to keep you in power. If you fail the vote tomorrow, you are ousted as Mayor instantly.",
      "turn_min": 12,
      "turn_max": 12,
      "war_mode": false,
      "options": [
        {
          "id": "A",
          "label": "Hand over key portfolios to the extortionate kingmaker parties.",
          "tag": "SAFE",
          "consequences": {
            "approval_delta": -15,
            "budget_delta": -100,
            "scandal_risk": 20,
            "advisor_effects": [
              {
                "advisor_id": "finance",
                "trust_delta": -20,
                "betrayal_risk_delta": 15
              }
            ]
          }
        },
        {
          "id": "B",
          "label": "Call their bluff, face the vote, and rely on public pressure.",
          "tag": "BOLD",
          "consequences": {
            "approval_delta": 25,
            "budget_delta": 0,
            "scandal_risk": 30,
            "advisor_effects": [
              {
                "advisor_id": "finance",
                "trust_delta": 15,
                "betrayal_risk_delta": -10
              }
            ]
          }
        },
        {
          "id": "C",
          "label": "Bribe opposition councilors with massive cash payouts to cross the floor.",
          "tag": "CHAOS",
          "consequences": {
            "approval_delta": -20,
            "budget_delta": -150,
            "scandal_risk": 90,
            "advisor_effects": [
              {
                "advisor_id": "finance",
                "trust_delta": -30,
                "betrayal_risk_delta": 25
              }
            ]
          }
        }
      ]
    }
  ],
  "scandals": [
    {
      "id": "tender_fraud",
      "title": "Massive PPE Tender Fraud Exposed",
      "description": "Journalists revealed that millions in municipal contracts were awarded to companies owned by your immediate family.",
      "severity_tier": "major",
      "approval_penalty": -22
    },
    {
      "id": "drunk_driving",
      "title": "Mayor Caught Fleeing Accident Scene",
      "description": "You crashed your official vehicle into a streetlight after a party and fled before the metro police arrived.",
      "severity_tier": "moderate",
      "approval_penalty": -12
    },
    {
      "id": "gupta_style_capture",
      "title": "State Capture Allegations Hit City Hall",
      "description": "Leaked emails show wealthy private businessmen dictating policy and cabinet appointments directly to your office.",
      "severity_tier": "career_ending",
      "approval_penalty": -40
    }
  ],
  "comment_library": {
    "positive": [
      "Finally some service delivery!",
      "Credit to the Mayor, this actually works.",
      "A rare win for Joburg.",
      "Let's hope they keep this momentum.",
      "Potholes fixed in my area today, shocking!",
      "Good job, just don't steal the money."
    ],
    "neutral": [
      "We'll see if it lasts past the elections.",
      "Eish, I don't trust these politicians.",
      "Whatever, just keep the lights on.",
      "Typical promises.",
      "Let's wait for the tender corruption to be exposed.",
      "Just another day in Egoli."
    ],
    "negative": [
      "Useless government!",
      "We are tired of voting for thieves.",
      "The city is collapsing and they do this?",
      "Load shedding is killing my business.",
      "Resign!",
      "We want service delivery now!"
    ],
    "media": [
      "The Star: Controversy surrounds the Mayor's latest directive.",
      "News24: Opposition demands answers over city budget.",
      "eNCA: Traffic at a standstill due to protests.",
      "Daily Maverick: The rot in Joburg's administration deepens.",
      "Radio 702: Callers express fury over continued power cuts.",
      "City Press: Is this the end of the coalition?"
    ],
    "politician": [
      "We will not stand for this corruption!",
      "A necessary step for our fiscal recovery.",
      "The ANC/DA/EFF must be held accountable.",
      "This is an attack on the poor.",
      "We urge patience while we rebuild.",
      "The previous administration left us a mess."
    ],
    "activist": [
      "Housing is a right, not a privilege!",
      "Stop privatizing our city!",
      "Water for all!",
      "End spatial apartheid now.",
      "We demand basic services.",
      "The elite protect their own."
    ],
    "street": [
      "Chommie, the taxis are striking again, I'm stuck.",
      "Stage 6 load shedding tonight, fetch the candles.",
      "Eish, my tires are gone because of these potholes.",
      "They only care about Sandton, bru.",
      "Nyaope is destroying our kids.",
      "Cable theft in my area, no power for 3 days."
    ],
    "crisis": [
      "The city is burning.",
      "Where are the police?!",
      "Total collapse, save yourselves.",
      "This is a disaster zone.",
      "We have no water, we are desperate.",
      "God save South Africa."
    ],
    "scandal": [
      "Thieves! All of them!",
      "They eat while we starve.",
      "Bring back the Scorpions.",
      "Absolutely shameless.",
      "Vote them out!",
      "We are led by criminals."
    ]
  },
  "scandal_reactions": {
    "minor": "Eish, just another tenderpreneur making money.",
    "moderate": "Disgusting, but not surprising in this country.",
    "major": "We will march to the Mayor's office tomorrow!",
    "career_ending": "You are going to prison. Finished and klaar."
  },
  "romance_exposure": {
    "severity": "minor",
    "flavour": "The tabloids love it, and there are jokes on Twitter, but it's quickly forgotten in the face of actual service delivery failures."
  }
}